<mockup version="5.2" minAllowVersion="5.2" ID="A8928151-4CA6-4C45-A3FA-F0D7BBACBDC2" platform="MtMobile" defaultW="360" defaultH="640" measureW="360" measureH="640" screenOrientation="MoPortrait" mobileScreenScale="1.77777779102325" clipArea="(0,0,0,0)">
  <controls controlCount="5">
    <control controlID="15D106A7-7354-44A2-B563-7155E51C6FFD" controlTypeID="Top ActionBar" x="0" y="20" w="360" h="48" zOrder="0">
      <color>4283164858</color>
      <links eventType="AtClick" animate="AmNone" animateAutoDelay="0" animateDuration="500">
        <link targetPageID="30D6E5A0-8A80-48F4-964A-9CADA4BBB19A" linkType="ltPageLink" isApplyIncludePage="False" title="Home">
          <area shape="0" alt="" ID="{6D04C4E8-8AA4-40E4-B300-CEF4B770208B}" coords="(2,4,42,44)"/>
        </link>
        <link targetPageID="" linkType="ltPageLink" isApplyIncludePage="False" title="Menu">
          <area shape="0" alt="" ID="{F01AC8C0-9C58-4502-A490-644D680509B9}" coords="(313,4,353,44)"/>
        </link>
      </links>
      <font family="Segoe+UI" displayName="Segoe+UI" postScript="" weightStyle="Regular" weight="400" isBold="False" isItalic="False"/>
      <text>3+Days+2+Night+in+Korea</text>
      <textSize>14</textSize>
      <lineSpacing>0</lineSpacing>
    </control>
    <control controlID="81CCCA46-8254-41E1-8C62-1C9731B61DC3" controlTypeID="StatusBar(Android)" x="0" y="0" w="360" h="20" zOrder="1"/>
    <control controlID="9B34DEBE-2A5F-4A63-900F-9F36BEDA5EAA" controlTypeID="Table" x="7" y="138" w="346" h="471" zOrder="2">
      <font family="Segoe+UI" displayName="Segoe+UI" postScript="" weightStyle="Regular" weight="400" isBold="False" isItalic="False"/>
      <text>Date%0D%0ATime%09Place%0D%0ALocation%09Activities%09Budget+Spends%092%2F6%2F2018%0D%0A9%3A00+AM%09Yeouido%2C+Seoul%2C+Korea%09Sight+Seeing%09RM+20%092%2F6%2F2018%0D%0A11%3A00+AM%09Sinchon+%26+Hongik%2C+Seoul%2C+Korea%09Visit+shops+and+food+trip%09RM+50%092%2F6%2F2018%0D%0A5%3A00+PM%09Myeongdong%2C+Seoul%2C+Korea%09Shopping%09RM+300%093%2F6%2F2018%0D%0A10%3A00+AM%09Gamcheon+Culture+Village%2C+Busan%2C+Korea%09Sight+Seeing+%22Rio+of+Korea%22%09RM+60%09Total+Expenditure%09Total+Expenditure%09Total+Expenditure%09RM+430</text>
      <textSize>14</textSize>
      <textAlign>HaCenter</textAlign>
      <lineSpacing>0</lineSpacing>
      <thickness>1</thickness>
      <dashMode>SdSolid</dashMode>
      <tableStyle>tsNone</tableStyle>
      <fontFamily/>
      <fontWeight>Regular</fontWeight>
      <textStyles>[]</textStyles>
      <cells>
        <cell rows="0,0" cols="0,0">
          <fontFamily>Segoe+UI</fontFamily>
          <fontWeight>Regular</fontWeight>
          <textStyles>[]</textStyles>
          <text>Date%0D%0ATime</text>
          <textHeight>44</textHeight>
          <font family="Segoe+UI" displayName="Segoe+UI" postScript="" weightStyle="Regular" weight="400" isBold="False" isItalic="False"/>
        </cell>
        <cell rows="0,0" cols="1,1">
          <fontFamily>Segoe+UI</fontFamily>
          <fontWeight>Regular</fontWeight>
          <textStyles>[]</textStyles>
          <text>Place%0D%0ALocation</text>
          <textHeight>44</textHeight>
          <font family="Segoe+UI" displayName="Segoe+UI" postScript="" weightStyle="Regular" weight="400" isBold="False" isItalic="False"/>
        </cell>
        <cell rows="0,0" cols="2,2">
          <fontFamily>Segoe+UI</fontFamily>
          <fontWeight>Regular</fontWeight>
          <textStyles>[]</textStyles>
          <text>Activities</text>
          <textHeight>28</textHeight>
          <font family="Segoe+UI" displayName="Segoe+UI" postScript="" weightStyle="Regular" weight="400" isBold="False" isItalic="False"/>
        </cell>
        <cell rows="0,0" cols="3,3">
          <fontFamily>Segoe+UI</fontFamily>
          <fontWeight>Regular</fontWeight>
          <textStyles>[]</textStyles>
          <text>Budget+Spends</text>
          <textHeight>44</textHeight>
          <font family="Segoe+UI" displayName="Segoe+UI" postScript="" weightStyle="Regular" weight="400" isBold="False" isItalic="False"/>
        </cell>
        <cell rows="1,1" cols="0,0">
          <fontFamily>Segoe+UI</fontFamily>
          <fontWeight>Regular</fontWeight>
          <textStyles>[]</textStyles>
          <text>2%2F6%2F2018%0D%0A9%3A00+AM</text>
          <textHeight>44</textHeight>
          <font family="Segoe+UI" displayName="Segoe+UI" postScript="" weightStyle="Regular" weight="400" isBold="False" isItalic="False"/>
        </cell>
        <cell rows="1,1" cols="1,1">
          <fontFamily>Segoe+UI</fontFamily>
          <fontWeight>Regular</fontWeight>
          <textStyles>[]</textStyles>
          <text>Yeouido%2C+Seoul%2C+Korea</text>
          <textHeight>44</textHeight>
          <font family="Segoe+UI" displayName="Segoe+UI" postScript="" weightStyle="Regular" weight="400" isBold="False" isItalic="False"/>
        </cell>
        <cell rows="1,1" cols="2,2">
          <fontFamily>Segoe+UI</fontFamily>
          <fontWeight>Regular</fontWeight>
          <textStyles>[]</textStyles>
          <text>Sight+Seeing</text>
          <textHeight>28</textHeight>
          <font family="Segoe+UI" displayName="Segoe+UI" postScript="" weightStyle="Regular" weight="400" isBold="False" isItalic="False"/>
        </cell>
        <cell rows="1,1" cols="3,3">
          <fontFamily>Segoe+UI</fontFamily>
          <fontWeight>Regular</fontWeight>
          <textStyles>[]</textStyles>
          <text>RM+20</text>
          <textHeight>28</textHeight>
          <font family="Segoe+UI" displayName="Segoe+UI" postScript="" weightStyle="Regular" weight="400" isBold="False" isItalic="False"/>
        </cell>
        <cell rows="2,2" cols="0,0">
          <fontFamily>Segoe+UI</fontFamily>
          <fontWeight>Regular</fontWeight>
          <textStyles>[]</textStyles>
          <text>2%2F6%2F2018%0D%0A11%3A00+AM</text>
          <textHeight>44</textHeight>
          <font family="Segoe+UI" displayName="Segoe+UI" postScript="" weightStyle="Regular" weight="400" isBold="False" isItalic="False"/>
        </cell>
        <cell rows="2,2" cols="1,1">
          <fontFamily>Segoe+UI</fontFamily>
          <fontWeight>Regular</fontWeight>
          <textStyles>[]</textStyles>
          <text>Sinchon+%26+Hongik%2C+Seoul%2C+Korea</text>
          <textHeight>60</textHeight>
          <font family="Segoe+UI" displayName="Segoe+UI" postScript="" weightStyle="Regular" weight="400" isBold="False" isItalic="False"/>
        </cell>
        <cell rows="2,2" cols="2,2">
          <fontFamily>Segoe+UI</fontFamily>
          <fontWeight>Regular</fontWeight>
          <textStyles>[]</textStyles>
          <text>Visit+shops+and+food+trip</text>
          <textHeight>44</textHeight>
          <font family="Segoe+UI" displayName="Segoe+UI" postScript="" weightStyle="Regular" weight="400" isBold="False" isItalic="False"/>
        </cell>
        <cell rows="2,2" cols="3,3">
          <fontFamily>Segoe+UI</fontFamily>
          <fontWeight>Regular</fontWeight>
          <textStyles>[]</textStyles>
          <text>RM+50</text>
          <textHeight>28</textHeight>
          <font family="Segoe+UI" displayName="Segoe+UI" postScript="" weightStyle="Regular" weight="400" isBold="False" isItalic="False"/>
        </cell>
        <cell rows="3,3" cols="0,0">
          <fontFamily>Segoe+UI</fontFamily>
          <fontWeight>Regular</fontWeight>
          <textStyles>[]</textStyles>
          <text>2%2F6%2F2018%0D%0A5%3A00+PM</text>
          <textHeight>44</textHeight>
          <font family="Segoe+UI" displayName="Segoe+UI" postScript="" weightStyle="Regular" weight="400" isBold="False" isItalic="False"/>
        </cell>
        <cell rows="3,3" cols="1,1">
          <fontFamily>Segoe+UI</fontFamily>
          <fontWeight>Regular</fontWeight>
          <textStyles>[]</textStyles>
          <text>Myeongdong%2C+Seoul%2C+Korea</text>
          <textHeight>44</textHeight>
          <font family="Segoe+UI" displayName="Segoe+UI" postScript="" weightStyle="Regular" weight="400" isBold="False" isItalic="False"/>
        </cell>
        <cell rows="3,3" cols="2,2">
          <fontFamily>Segoe+UI</fontFamily>
          <fontWeight>Regular</fontWeight>
          <textStyles>[]</textStyles>
          <text>Shopping</text>
          <textHeight>28</textHeight>
          <font family="Segoe+UI" displayName="Segoe+UI" postScript="" weightStyle="Regular" weight="400" isBold="False" isItalic="False"/>
        </cell>
        <cell rows="3,3" cols="3,3">
          <fontFamily>Segoe+UI</fontFamily>
          <fontWeight>Regular</fontWeight>
          <textStyles>[]</textStyles>
          <text>RM+300</text>
          <textHeight>28</textHeight>
          <font family="Segoe+UI" displayName="Segoe+UI" postScript="" weightStyle="Regular" weight="400" isBold="False" isItalic="False"/>
        </cell>
        <cell rows="4,4" cols="0,0">
          <fontFamily>Segoe+UI</fontFamily>
          <fontWeight>Regular</fontWeight>
          <textStyles>[]</textStyles>
          <text>3%2F6%2F2018%0D%0A10%3A00+AM</text>
          <textHeight>44</textHeight>
          <font family="Segoe+UI" displayName="Segoe+UI" postScript="" weightStyle="Regular" weight="400" isBold="False" isItalic="False"/>
        </cell>
        <cell rows="4,4" cols="1,1">
          <fontFamily>Segoe+UI</fontFamily>
          <fontWeight>Regular</fontWeight>
          <textStyles>[]</textStyles>
          <text>Gamcheon+Culture+Village%2C+Busan%2C+Korea</text>
          <textHeight>76</textHeight>
          <font family="Segoe+UI" displayName="Segoe+UI" postScript="" weightStyle="Regular" weight="400" isBold="False" isItalic="False"/>
        </cell>
        <cell rows="4,4" cols="2,2">
          <fontFamily>Segoe+UI</fontFamily>
          <fontWeight>Regular</fontWeight>
          <textStyles>[]</textStyles>
          <text>Sight+Seeing+%22Rio+of+Korea%22</text>
          <textHeight>44</textHeight>
          <font family="Segoe+UI" displayName="Segoe+UI" postScript="" weightStyle="Regular" weight="400" isBold="False" isItalic="False"/>
        </cell>
        <cell rows="4,4" cols="3,3">
          <fontFamily>Segoe+UI</fontFamily>
          <fontWeight>Regular</fontWeight>
          <textStyles>[]</textStyles>
          <text>RM+60</text>
          <textHeight>28</textHeight>
          <font family="Segoe+UI" displayName="Segoe+UI" postScript="" weightStyle="Regular" weight="400" isBold="False" isItalic="False"/>
        </cell>
        <cell rows="5,5" cols="0,2">
          <fontFamily>Segoe+UI</fontFamily>
          <fontWeight>Regular</fontWeight>
          <textStyles>[]</textStyles>
          <text>Total+Expenditure</text>
          <textHeight>28</textHeight>
          <font family="Segoe+UI" displayName="Segoe+UI" postScript="" weightStyle="Regular" weight="400" isBold="False" isItalic="False"/>
        </cell>
        <cell rows="5,5" cols="3,3">
          <fontFamily>Segoe+UI</fontFamily>
          <fontWeight>Regular</fontWeight>
          <textStyles>[]</textStyles>
          <text>RM+430</text>
          <textHeight>28</textHeight>
          <font family="Segoe+UI" displayName="Segoe+UI" postScript="" weightStyle="Regular" weight="400" isBold="False" isItalic="False"/>
        </cell>
      </cells>
      <rows>
        <row height="44">
          <fontFamily/>
          <fontWeight>Regular</fontWeight>
          <textStyles>[]</textStyles>
          <isAutoRowHeight>True</isAutoRowHeight>
        </row>
        <row height="94">
          <fontFamily/>
          <fontWeight>Regular</fontWeight>
          <textStyles>[]</textStyles>
          <isAutoRowHeight>False</isAutoRowHeight>
        </row>
        <row height="94">
          <fontFamily/>
          <fontWeight>Regular</fontWeight>
          <textStyles>[]</textStyles>
          <isAutoRowHeight>False</isAutoRowHeight>
        </row>
        <row height="94">
          <fontFamily/>
          <fontWeight>Regular</fontWeight>
          <textStyles>[]</textStyles>
          <isAutoRowHeight>False</isAutoRowHeight>
        </row>
        <row height="94">
          <fontFamily/>
          <fontWeight>Regular</fontWeight>
          <textStyles>[]</textStyles>
          <isAutoRowHeight>False</isAutoRowHeight>
        </row>
        <row height="51">
          <fontFamily/>
          <fontWeight>Regular</fontWeight>
          <textStyles>[]</textStyles>
          <isAutoRowHeight>False</isAutoRowHeight>
        </row>
      </rows>
      <cols>
        <col width="85">
          <fontFamily/>
          <fontWeight>Regular</fontWeight>
          <textStyles>[]</textStyles>
        </col>
        <col width="86">
          <fontFamily/>
          <fontWeight>Regular</fontWeight>
          <textStyles>[]</textStyles>
        </col>
        <col width="87">
          <fontFamily/>
          <fontWeight>Regular</fontWeight>
          <textStyles>[]</textStyles>
        </col>
        <col width="88">
          <fontFamily/>
          <fontWeight>Regular</fontWeight>
          <textStyles>[]</textStyles>
        </col>
      </cols>
    </control>
    <control controlID="EB2ADFED-AA07-41AF-ACBA-A9977D23CF76" controlTypeID="Tabs" x="0" y="68" w="360" h="35" zOrder="3">
      <links eventType="AtClick" animate="AmNone" animateAutoDelay="0" animateDuration="500">
        <link targetPageID="" linkType="ltPageLink" isApplyIncludePage="False" title="Day+1">
          <area shape="0" alt="" ID="{B3B3DBBC-07CE-4CA7-819B-DCE5EABAB5B9}" coords="(0,0,59,35)"/>
        </link>
        <link targetPageID="" linkType="ltPageLink" isApplyIncludePage="False" title="+Day+2">
          <area shape="0" alt="" ID="{80DB7A90-94B3-4D03-8F86-332C24470D0A}" coords="(60,0,119,35)"/>
        </link>
        <link targetPageID="" linkType="ltPageLink" isApplyIncludePage="False" title="+Day+3">
          <area shape="0" alt="" ID="{6D25A6E6-6814-43B3-B647-DAA58A46F36A}" coords="(120,0,179,35)"/>
        </link>
        <link targetPageID="80C93B70-87D6-4800-A3DE-2626C50C0535" linkType="ltPageLink" isApplyIncludePage="False" title="+Photos">
          <area shape="0" alt="" ID="{F54B9191-32CC-4EBB-AC08-7CC0C1B741D6}" coords="(180,0,239,35)"/>
        </link>
        <link targetPageID="7498A609-0CB5-422C-BA6F-820370E4198C" linkType="ltPageLink" isApplyIncludePage="False" title="+Budget">
          <area shape="0" alt="" ID="{5AF5EB67-0665-4606-A19B-A3B77680398E}" coords="(240,0,299,35)"/>
        </link>
        <link targetPageID="DA2482EA-32F0-4325-ABCC-EAF5E116C0AA" linkType="ltPageLink" isApplyIncludePage="False" title="+Comments">
          <area shape="0" alt="" ID="{0CBABC90-D31D-4C90-A416-50410CB9CA9F}" coords="(300,0,359,35)"/>
        </link>
      </links>
      <font family="Segoe+UI" displayName="Segoe+UI" postScript="" weightStyle="Regular" weight="400" isBold="False" isItalic="False"/>
      <text>Day+1%2C+Day+2%2C+Day+3%2C+Photos%2C+Budget%2C+Comments</text>
      <textSize>14</textSize>
      <lineSpacing>0</lineSpacing>
      <selectedColor>4293557799</selectedColor>
    </control>
    <control controlID="7FAB4E13-CDCC-4592-9699-4034F4811EC2" controlTypeID="Label" x="10" y="109" w="85" h="19" zOrder="4">
      <font family="Segoe+UI" displayName="Segoe+UI" postScript="" weightStyle="Regular" weight="400" isBold="False" isItalic="False"/>
      <text>By%3A+Tony+Stark</text>
      <lineSpacing>0</lineSpacing>
      <selectedIndex>-1</selectedIndex>
    </control>
  </controls>
  <param>
    <backgroundColor>4294967295</backgroundColor>
    <fontSize>0</fontSize>
    <fontFamily/>
    <guideLines/>
  </param>
</mockup>